styled_str/__init__.py
styled_str/styled.py
styled_str-0.1.0.dist-info/LICENSE
styled_str-0.1.0.dist-info/METADATA
styled_str-0.1.0.dist-info/WHEEL
styled_str-0.1.0.dist-info/top_level.txt
styled_str-0.1.0.dist-info/RECORD
