Metadata-Version: 2.1
Name: styled-str
Version: 0.1.0
Summary: Colored text output in Python using ANSI escape sequences.
Home-page: https://github.com/jeremyephron/styled-str
Author: Jeremy Ephron
Author-email: jeremyephron@gmail.com
License: UNKNOWN
Platform: UNKNOWN
Classifier: Programming Language :: Python
Classifier: Programming Language :: Python :: 3
Classifier: License :: OSI Approved :: MIT License
Classifier: Operating System :: MacOS
